{"events":
    [
        {
            "id":29,
            "active":true,
            "customerID":421,
            "customer":"תעשיה אוירית",
            "taskNumber":1671,
            "project":"ACF POC",
            "subProject":"תעשיה אוירית ACF POC",
            "priority":0,
            "TAG":"ELTAACF",
            "MODEL":"T&M",
            "Cynefin":"4",
            "RANK":"0",
            "OWNER":"Hanokh",
            "desirableManpower":3,
            "actualManpower":3,
            "manpower":"Vadim, Chavi, Yafit",
            "startDate":"14/11/2017",
            "EstimatedDate":"14/11/2018",
            "ActualFinishDate":"14/11/2017",
            "JIRA":"ELTAACF",
            "jenkins":"https://sharepoint.ngsoft.com/Keren%20Or/Home.aspx",
            "sharepoint":"https://sharepoint.ngsoft.com/Keren%20Or/Home.aspx",
            "SVN":"https://sharepoint.ngsoft.com/Keren%20Or/Home.aspx",
            "documentedSTR":"",
            "Linter":"",
            "ELK":"",	
            "productionSite":"https://sharepoint.ngsoft.com/Keren%20Or/Home.aspx",
            "URLToDemoSite":"https://sharepoint.ngsoft.com/Keren%20Or/Home.aspx"
        },
        {
            "id":29,
            "active":true,
            "customerID":421,
            "customer":"קרן אור",
            "taskNumber":1671,
            "project":"קרן אור",
            "subProject":"קרן אור קרן אור",
            "priority":0,
            "TAG":"KCA",
            "MODEL":"FIX",
            "Cynefin":"4",
            "RANK":"0",
            "OWNER":"sveta",
            "desirableManpower":3,
            "actualManpower":3,
            "manpower":"",
            "startDate":"14/11/2017",
            "EstimatedDate":"14/11/2018",
            "ActualFinishDate":"14/11/2017",
            "JIRA":"ELTAACF",
            "jenkins":"https://sharepoint.ngsoft.com/Keren%20Or/Home.aspx",
            "sharepoint":"https://sharepoint.ngsoft.com/Keren%20Or/Home.aspx",
            "SVN":"https://sharepoint.ngsoft.com/Keren%20Or/Home.aspx",
            "documentedSTR":"",
            "Linter":"",
            "ELK":"",	
            "productionSite":"https://sharepoint.ngsoft.com/Keren%20Or/Home.aspx",
            "URLToDemoSite":"https://sharepoint.ngsoft.com/Keren%20Or/Home.aspx"
        },
        {
            "id":29,
            "active":true,
            "customerID":421,
            "customer":"תוכנית אב לתחבורה - ירושלים",
            "taskNumber":1671,
            "project":"מערכת RAMS",
            "subProject":"תוכנית אב לתחבורה - ירושלים מערכת RAMS",
            "priority":0,
            "TAG":"JTMTRAMS",
            "MODEL":"FIX",
            "Cynefin":"4",
            "RANK":"0",
            "OWNER":"oren",
            "desirableManpower":3,
            "actualManpower":3,
            "manpower":"Vadim, Chavi, Yafit",
            "startDate":"14/11/2017",
            "EstimatedDate":"14/11/2018",
            "ActualFinishDate":"14/11/2017",
            "JIRA":"ELTAACF",
            "jenkins":"https://sharepoint.ngsoft.com/Keren%20Or/Home.aspx",
            "sharepoint":"https://sharepoint.ngsoft.com/Keren%20Or/Home.aspx",
            "SVN":"https://sharepoint.ngsoft.com/Keren%20Or/Home.aspx",
            "documentedSTR":"",
            "Linter":"",
            "ELK":"",	
            "productionSite":"https://sharepoint.ngsoft.com/Keren%20Or/Home.aspx",
            "URLToDemoSite":"https://sharepoint.ngsoft.com/Keren%20Or/Home.aspx"
        }
    ]
}